invisicode.py
invisicode-1.1.1.dist-info/METADATA
invisicode-1.1.1.dist-info/WHEEL
invisicode-1.1.1.dist-info/licenses/LICENSE
invisicode-1.1.1.dist-info/RECORD
