Metadata-Version: 2.4
Name: invisicode
Version: 1.1.1
Summary: Fast and efficient coding of binary data into non-breaking unicode whitespace
Project-URL: Homepage, https://github.com/thomas-xin/invisicode
Project-URL: Repository, https://github.com/thomas-xin/invisicode
Project-URL: Issues, https://github.com/thomas-xin/invisicode/issues
Author-email: Thomas Xin <thomasxin@gmail.com>
License: Unlicense
License-File: LICENSE
Classifier: Programming Language :: Python :: 3
Requires-Python: >=3.8
Requires-Dist: numpy>=2.2.6
